{
  "station_id": "YCAMS",
  "station_name": "American Spirit",
  "timestamp": "2026-07-10T21:59:02.015008",
  "data": {
    "headers": [
      "Date/Time\u00a0(L)",
      "Temp.\u00a0(\u00b0F)",
      "DewPoint(\u00b0F)",
      "RelativeHumidity(%)",
      "WindChill(\u00b0F)",
      "WindDirection",
      "WindSpeed(mph)"
    ],
    "rows": [
      [
        "Jul 10, 3:00 pm",
        "69",
        "33",
        "26",
        "",
        "NNW",
        "7G21"
      ],
      [
        "Jul 10, 2:00 pm",
        "67",
        "34",
        "30",
        "",
        "NNW",
        "6G20"
      ],
      [
        "Jul 10, 1:00 pm",
        "67",
        "34",
        "29",
        "",
        "NW",
        "6G20"
      ],
      [
        "Jul 10, 12:00 pm",
        "65",
        "33",
        "30",
        "",
        "WSW",
        "6G17"
      ],
      [
        "Jul 10, 11:00 am",
        "64",
        "33",
        "32",
        "",
        "SW",
        "5G14"
      ],
      [
        "Jul 10, 10:00 am",
        "64",
        "38",
        "38",
        "",
        "NNE",
        "3G12"
      ],
      [
        "Jul 10, 9:00 am",
        "62",
        "40",
        "45",
        "",
        "NNE",
        "2G6"
      ],
      [
        "Jul 10, 8:00 am",
        "60",
        "38",
        "45",
        "",
        "E",
        "2G5"
      ],
      [
        "Jul 10, 7:00 am",
        "59",
        "37",
        "44",
        "",
        "SE",
        "2G5"
      ],
      [
        "Jul 10, 6:00 am",
        "56",
        "36",
        "48",
        "",
        "SSE",
        "5G6"
      ],
      [
        "Jul 10, 5:00 am",
        "56",
        "35",
        "46",
        "",
        "SSE",
        "5G6"
      ],
      [
        "Jul 10, 4:00 am",
        "57",
        "34",
        "42",
        "",
        "SSE",
        "3G7"
      ],
      [
        "Jul 10, 3:00 am",
        "61",
        "36",
        "39",
        "",
        "WNW",
        "4G9"
      ],
      [
        "Jul 10, 2:00 am",
        "61",
        "35",
        "38",
        "",
        "WSW",
        "6G14"
      ],
      [
        "Jul 10, 1:00 am",
        "61",
        "34",
        "37",
        "",
        "WSW",
        "11G15"
      ],
      [
        "Jul 10, 12:00 am",
        "62",
        "30",
        "30",
        "",
        "WSW",
        "11G17"
      ],
      [
        "Jul 9, 11:00 pm",
        "62",
        "27",
        "26",
        "",
        "W",
        "4G7"
      ],
      [
        "Jul 9, 10:00 pm",
        "63",
        "26",
        "25",
        "",
        "W",
        "6G13"
      ],
      [
        "Jul 9, 9:00 pm",
        "65",
        "28",
        "25",
        "",
        "NW",
        "10G15"
      ],
      [
        "Jul 9, 8:00 pm",
        "67",
        "27",
        "22",
        "",
        "NNW",
        "13G23"
      ],
      [
        "Jul 9, 7:00 pm",
        "68",
        "29",
        "23",
        "",
        "NW",
        "14G23"
      ],
      [
        "Jul 9, 6:00 pm",
        "67",
        "32",
        "27",
        "",
        "NW",
        "12G26"
      ],
      [
        "Jul 9, 5:00 pm",
        "67",
        "33",
        "28",
        "",
        "NW",
        "12G30"
      ],
      [
        "Jul 9, 4:00 pm",
        "66",
        "34",
        "30",
        "",
        "NW",
        "11G22"
      ],
      [
        "Jul 9, 3:00 pm",
        "65",
        "33",
        "31",
        "",
        "NW",
        "11G24"
      ],
      [
        "Jul 9, 2:00 pm",
        "64",
        "33",
        "31",
        "",
        "NW",
        "11G23"
      ],
      [
        "Jul 9, 1:00 pm",
        "63",
        "35",
        "35",
        "",
        "NW",
        "13G24"
      ],
      [
        "Jul 9, 12:00 pm",
        "63",
        "35",
        "35",
        "",
        "NNW",
        "10G22"
      ],
      [
        "Jul 9, 11:00 am",
        "62",
        "35",
        "37",
        "",
        "NNW",
        "6G23"
      ],
      [
        "Jul 9, 10:00 am",
        "61",
        "42",
        "50",
        "",
        "NNE",
        "3G13"
      ],
      [
        "Jul 9, 9:00 am",
        "59",
        "38",
        "46",
        "",
        "NE",
        "3G10"
      ],
      [
        "Jul 9, 8:00 am",
        "56",
        "36",
        "48",
        "",
        "NE",
        "4G13"
      ],
      [
        "Jul 9, 7:00 am",
        "54",
        "36",
        "50",
        "",
        "WSW",
        "9G15"
      ],
      [
        "Jul 9, 6:00 am",
        "54",
        "36",
        "50",
        "",
        "WSW",
        "3G8"
      ],
      [
        "Jul 9, 5:00 am",
        "54",
        "35",
        "48",
        "",
        "SW",
        "3G10"
      ],
      [
        "Jul 9, 4:00 am",
        "55",
        "35",
        "47",
        "",
        "NW",
        "4G13"
      ],
      [
        "Jul 9, 3:00 am",
        "54",
        "35",
        "49",
        "",
        "NW",
        "5G11"
      ],
      [
        "Jul 9, 2:00 am",
        "56",
        "35",
        "45",
        "",
        "WNW",
        "7G22"
      ],
      [
        "Jul 9, 1:00 am",
        "51",
        "40",
        "67",
        "",
        "W",
        "5G24"
      ],
      [
        "Jul 9, 12:00 am",
        "48",
        "40",
        "75",
        "47",
        "SE",
        "4G9"
      ],
      [
        "Jul 8, 11:00 pm",
        "49",
        "42",
        "77",
        "43",
        "WNW",
        "18G38"
      ],
      [
        "Jul 8, 10:00 pm",
        "55",
        "42",
        "61",
        "",
        "W",
        "11G47"
      ],
      [
        "Jul 8, 9:00 pm",
        "56",
        "41",
        "58",
        "",
        "S",
        "4G11"
      ],
      [
        "Jul 8, 8:00 pm",
        "58",
        "40",
        "52",
        "",
        "W",
        "7G20"
      ],
      [
        "Jul 8, 7:00 pm",
        "64",
        "36",
        "36",
        "",
        "WNW",
        "11G31"
      ],
      [
        "Jul 8, 6:00 pm",
        "69",
        "32",
        "25",
        "",
        "NNW",
        "9G21"
      ],
      [
        "Jul 8, 5:00 pm",
        "69",
        "34",
        "28",
        "",
        "NNW",
        "7G19"
      ],
      [
        "Jul 8, 4:00 pm",
        "69",
        "34",
        "27",
        "",
        "WNW",
        "6G15"
      ],
      [
        "Jul 8, 3:00 pm",
        "67",
        "34",
        "29",
        "",
        "NW",
        "11G26"
      ],
      [
        "Jul 8, 2:00 pm",
        "67",
        "34",
        "29",
        "",
        "NNW",
        "10G24"
      ],
      [
        "Jul 8, 1:00 pm",
        "67",
        "33",
        "28",
        "",
        "SW",
        "5G17"
      ],
      [
        "Jul 8, 12:00 pm",
        "66",
        "39",
        "37",
        "",
        "ENE",
        "5G14"
      ],
      [
        "Jul 8, 11:00 am",
        "63",
        "39",
        "42",
        "",
        "ESE",
        "6G12"
      ],
      [
        "Jul 8, 10:00 am",
        "63",
        "41",
        "44",
        "",
        "E",
        "4G9"
      ],
      [
        "Jul 8, 9:00 am",
        "63",
        "40",
        "43",
        "",
        "NNE",
        "1G5"
      ],
      [
        "Jul 8, 8:00 am",
        "61",
        "38",
        "42",
        "",
        "N",
        "2G6"
      ],
      [
        "Jul 8, 7:00 am",
        "59",
        "35",
        "40",
        "",
        "WNW",
        "4G11"
      ],
      [
        "Jul 8, 6:00 am",
        "58",
        "34",
        "41",
        "",
        "WSW",
        "6G10"
      ],
      [
        "Jul 8, 5:00 am",
        "58",
        "34",
        "40",
        "",
        "SW",
        "6G11"
      ],
      [
        "Jul 8, 4:00 am",
        "59",
        "34",
        "39",
        "",
        "SW",
        "7G13"
      ],
      [
        "Jul 8, 3:00 am",
        "60",
        "34",
        "38",
        "",
        "SW",
        "5G10"
      ],
      [
        "Jul 8, 2:00 am",
        "57",
        "39",
        "51",
        "",
        "WSW",
        "3G6"
      ],
      [
        "Jul 8, 1:00 am",
        "55",
        "40",
        "57",
        "",
        "W",
        "2G4"
      ],
      [
        "Jul 8, 12:00 am",
        "57",
        "40",
        "54",
        "",
        "SSW",
        "3G5"
      ],
      [
        "Jul 7, 11:00 pm",
        "60",
        "37",
        "43",
        "",
        "WSW",
        "2G4"
      ],
      [
        "Jul 7, 10:00 pm",
        "61",
        "38",
        "42",
        "",
        "WNW",
        "4G6"
      ],
      [
        "Jul 7, 9:00 pm",
        "63",
        "38",
        "39",
        "",
        "NW",
        "7G12"
      ],
      [
        "Jul 7, 8:00 pm",
        "63",
        "36",
        "37",
        "",
        "NW",
        "13G19"
      ],
      [
        "Jul 7, 7:00 pm",
        "64",
        "37",
        "37",
        "",
        "NW",
        "15G22"
      ],
      [
        "Jul 7, 6:00 pm",
        "65",
        "39",
        "38",
        "",
        "NW",
        "17G26"
      ],
      [
        "Jul 7, 5:00 pm",
        "66",
        "40",
        "39",
        "",
        "NNW",
        "16G26"
      ],
      [
        "Jul 7, 4:00 pm",
        "65",
        "39",
        "39",
        "",
        "NW",
        "15G28"
      ],
      [
        "Jul 7, 3:00 pm",
        "64",
        "36",
        "36",
        "",
        "NW",
        "14G33"
      ],
      [
        "Jul 7, 2:00 pm",
        "63",
        "35",
        "35",
        "",
        "NNW",
        "14G30"
      ],
      [
        "Jul 7, 1:00 pm",
        "62",
        "37",
        "40",
        "",
        "NNW",
        "12G25"
      ],
      [
        "Jul 7, 12:00 pm",
        "61",
        "39",
        "45",
        "",
        "NNW",
        "10G25"
      ],
      [
        "Jul 7, 11:00 am",
        "60",
        "40",
        "48",
        "",
        "NNW",
        "11G24"
      ],
      [
        "Jul 7, 10:00 am",
        "61",
        "43",
        "51",
        "",
        "N",
        "5G17"
      ],
      [
        "Jul 7, 9:00 am",
        "58",
        "46",
        "64",
        "",
        "NE",
        "4G13"
      ],
      [
        "Jul 7, 8:00 am",
        "57",
        "45",
        "65",
        "",
        "E",
        "4G7"
      ],
      [
        "Jul 7, 7:00 am",
        "55",
        "43",
        "63",
        "",
        "SW",
        "3G9"
      ],
      [
        "Jul 7, 6:00 am",
        "52",
        "42",
        "68",
        "",
        "SSE",
        "2G5"
      ],
      [
        "Jul 7, 5:00 am",
        "50",
        "44",
        "79",
        "",
        "WNW",
        "2G4"
      ],
      [
        "Jul 7, 4:00 am",
        "49",
        "44",
        "83",
        "",
        "SSE",
        "2G6"
      ],
      [
        "Jul 7, 3:00 am",
        "51",
        "44",
        "76",
        "",
        "SSE",
        "2G6"
      ],
      [
        "Jul 7, 2:00 am",
        "49",
        "45",
        "85",
        "49",
        "W",
        "3G5"
      ],
      [
        "Jul 7, 1:00 am",
        "51",
        "45",
        "79",
        "",
        "S",
        "4G8"
      ],
      [
        "Jul 7, 12:00 am",
        "52",
        "44",
        "75",
        "",
        "WNW",
        "7G15"
      ],
      [
        "Jul 6, 11:00 pm",
        "52",
        "45",
        "76",
        "",
        "WNW",
        "12G22"
      ],
      [
        "Jul 6, 10:00 pm",
        "53",
        "44",
        "73",
        "",
        "SE",
        "4G16"
      ],
      [
        "Jul 6, 9:00 pm",
        "54",
        "46",
        "75",
        "",
        "SE",
        "8G14"
      ],
      [
        "Jul 6, 8:00 pm",
        "58",
        "45",
        "62",
        "",
        "N",
        "5G15"
      ],
      [
        "Jul 6, 7:00 pm",
        "58",
        "43",
        "58",
        "",
        "W",
        "12G30"
      ],
      [
        "Jul 6, 6:00 pm",
        "67",
        "36",
        "32",
        "",
        "S",
        "6G18"
      ],
      [
        "Jul 6, 5:00 pm",
        "69",
        "36",
        "30",
        "",
        "SSW",
        "6G18"
      ],
      [
        "Jul 6, 4:00 pm",
        "68",
        "40",
        "36",
        "",
        "ENE",
        "4G13"
      ],
      [
        "Jul 6, 3:00 pm",
        "63",
        "41",
        "45",
        "",
        "ESE",
        "4G10"
      ],
      [
        "Jul 6, 2:00 pm",
        "63",
        "38",
        "40",
        "",
        "E",
        "6G15"
      ],
      [
        "Jul 6, 1:00 pm",
        "60",
        "38",
        "45",
        "",
        "ESE",
        "5G22"
      ],
      [
        "Jul 6, 12:00 pm",
        "59",
        "41",
        "52",
        "",
        "ESE",
        "4G12"
      ],
      [
        "Jul 6, 11:00 am",
        "59",
        "41",
        "52",
        "",
        "ESE",
        "3G10"
      ],
      [
        "Jul 6, 10:00 am",
        "58",
        "39",
        "49",
        "",
        "SE",
        "3G8"
      ],
      [
        "Jul 6, 9:00 am",
        "56",
        "38",
        "51",
        "",
        "SE",
        "3G7"
      ],
      [
        "Jul 6, 8:00 am",
        "55",
        "36",
        "48",
        "",
        "SSE",
        "3G5"
      ],
      [
        "Jul 6, 7:00 am",
        "55",
        "35",
        "47",
        "",
        "SE",
        "6G9"
      ],
      [
        "Jul 6, 6:00 am",
        "56",
        "34",
        "43",
        "",
        "SE",
        "6G9"
      ],
      [
        "Jul 6, 5:00 am",
        "56",
        "34",
        "44",
        "",
        "SSE",
        "6G8"
      ],
      [
        "Jul 6, 4:00 am",
        "54",
        "35",
        "48",
        "",
        "SSE",
        "1G3"
      ],
      [
        "Jul 6, 3:00 am",
        "56",
        "33",
        "42",
        "",
        "SE",
        "3G5"
      ],
      [
        "Jul 6, 2:00 am",
        "56",
        "34",
        "43",
        "",
        "SW",
        "3G7"
      ],
      [
        "Jul 6, 1:00 am",
        "55",
        "35",
        "47",
        "",
        "SSE",
        "4G9"
      ],
      [
        "Jul 6, 12:00 am",
        "56",
        "36",
        "48",
        "",
        "W",
        "8G21"
      ],
      [
        "Jul 5, 11:00 pm",
        "57",
        "37",
        "47",
        "",
        "NW",
        "15G28"
      ],
      [
        "Jul 5, 10:00 pm",
        "62",
        "30",
        "30",
        "",
        "W",
        "7G25"
      ],
      [
        "Jul 5, 9:00 pm",
        "60",
        "34",
        "38",
        "",
        "WSW",
        "3G16"
      ],
      [
        "Jul 5, 8:00 pm",
        "60",
        "37",
        "43",
        "",
        "N",
        "2G5"
      ],
      [
        "Jul 5, 7:00 pm",
        "60",
        "37",
        "43",
        "",
        "WNW",
        "6G19"
      ],
      [
        "Jul 5, 6:00 pm",
        "60",
        "36",
        "41",
        "",
        "NW",
        "6G18"
      ],
      [
        "Jul 5, 5:00 pm",
        "57",
        "38",
        "50",
        "",
        "NW",
        "7G20"
      ],
      [
        "Jul 5, 4:00 pm",
        "56",
        "38",
        "51",
        "",
        "NW",
        "14G29"
      ],
      [
        "Jul 5, 3:00 pm",
        "63",
        "34",
        "34",
        "",
        "NW",
        "14G44"
      ],
      [
        "Jul 5, 2:00 pm",
        "68",
        "31",
        "25",
        "",
        "SE",
        "5G19"
      ],
      [
        "Jul 5, 1:00 pm",
        "69",
        "31",
        "24",
        "",
        "NW",
        "5G18"
      ],
      [
        "Jul 5, 12:00 pm",
        "67",
        "29",
        "24",
        "",
        "NW",
        "7G18"
      ],
      [
        "Jul 5, 11:00 am",
        "67",
        "29",
        "24",
        "",
        "NNW",
        "4G16"
      ],
      [
        "Jul 5, 10:00 am",
        "66",
        "32",
        "28",
        "",
        "NE",
        "5G18"
      ],
      [
        "Jul 5, 9:00 am",
        "64",
        "31",
        "29",
        "",
        "ENE",
        "5G12"
      ],
      [
        "Jul 5, 8:00 am",
        "63",
        "30",
        "29",
        "",
        "ENE",
        "3G9"
      ],
      [
        "Jul 5, 7:00 am",
        "60",
        "28",
        "30",
        "",
        "SSW",
        "7G13"
      ],
      [
        "Jul 5, 6:00 am",
        "59",
        "28",
        "31",
        "",
        "SW",
        "9G13"
      ],
      [
        "Jul 5, 5:00 am",
        "59",
        "27",
        "30",
        "",
        "SW",
        "9G14"
      ],
      [
        "Jul 5, 4:00 am",
        "60",
        "27",
        "29",
        "",
        "SW",
        "10G14"
      ],
      [
        "Jul 5, 3:00 am",
        "61",
        "28",
        "28",
        "",
        "SW",
        "12G18"
      ],
      [
        "Jul 5, 2:00 am",
        "62",
        "27",
        "27",
        "",
        "SSW",
        "5G16"
      ],
      [
        "Jul 5, 1:00 am",
        "62",
        "27",
        "26",
        "",
        "SW",
        "5G13"
      ],
      [
        "Jul 5, 12:00 am",
        "62",
        "27",
        "27",
        "",
        "SW",
        "5G12"
      ],
      [
        "Jul 4, 11:00 pm",
        "62",
        "30",
        "30",
        "",
        "SW",
        "5G9"
      ],
      [
        "Jul 4, 10:00 pm",
        "63",
        "30",
        "29",
        "",
        "S",
        "3G8"
      ],
      [
        "Jul 4, 9:00 pm",
        "65",
        "33",
        "30",
        "",
        "E",
        "3G8"
      ],
      [
        "Jul 4, 8:00 pm",
        "66",
        "32",
        "28",
        "",
        "S",
        "3G11"
      ],
      [
        "Jul 4, 7:00 pm",
        "66",
        "30",
        "26",
        "",
        "SSW",
        "4G14"
      ],
      [
        "Jul 4, 6:00 pm",
        "67",
        "29",
        "24",
        "",
        "NW",
        "7G21"
      ],
      [
        "Jul 4, 5:00 pm",
        "66",
        "27",
        "23",
        "",
        "NW",
        "7G25"
      ],
      [
        "Jul 4, 4:00 pm",
        "66",
        "27",
        "23",
        "",
        "NNW",
        "7G20"
      ],
      [
        "Jul 4, 3:00 pm",
        "65",
        "32",
        "29",
        "",
        "NNW",
        "8G23"
      ],
      [
        "Jul 4, 2:00 pm",
        "63",
        "35",
        "35",
        "",
        "NW",
        "8G22"
      ],
      [
        "Jul 4, 1:00 pm",
        "61",
        "33",
        "35",
        "",
        "NW",
        "8G23"
      ],
      [
        "Jul 4, 12:00 pm",
        "61",
        "32",
        "33",
        "",
        "NNW",
        "7G23"
      ],
      [
        "Jul 4, 11:00 am",
        "61",
        "32",
        "33",
        "",
        "NNW",
        "5G18"
      ],
      [
        "Jul 4, 10:00 am",
        "60",
        "33",
        "37",
        "",
        "NNE",
        "4G12"
      ],
      [
        "Jul 4, 9:00 am",
        "58",
        "33",
        "39",
        "",
        "NNE",
        "3G10"
      ],
      [
        "Jul 4, 8:00 am",
        "57",
        "31",
        "38",
        "",
        "SSW",
        "4G12"
      ],
      [
        "Jul 4, 7:00 am",
        "55",
        "31",
        "40",
        "",
        "SW",
        "6G9"
      ],
      [
        "Jul 4, 6:00 am",
        "53",
        "30",
        "42",
        "",
        "SW",
        "6G9"
      ],
      [
        "Jul 4, 5:00 am",
        "53",
        "30",
        "41",
        "",
        "WSW",
        "6G10"
      ],
      [
        "Jul 4, 4:00 am",
        "52",
        "32",
        "46",
        "",
        "WSW",
        "3G11"
      ],
      [
        "Jul 4, 3:00 am",
        "52",
        "33",
        "48",
        "",
        "SSE",
        "2G4"
      ],
      [
        "Jul 4, 2:00 am",
        "54",
        "32",
        "43",
        "",
        "WSW",
        "4G7"
      ],
      [
        "Jul 4, 1:00 am",
        "53",
        "33",
        "46",
        "",
        "S",
        "2G7"
      ],
      [
        "Jul 4, 12:00 am",
        "55",
        "32",
        "41",
        "",
        "S",
        "5G8"
      ],
      [
        "Jul 3, 11:00 pm",
        "56",
        "30",
        "37",
        "",
        "W",
        "4G6"
      ],
      [
        "Jul 3, 10:00 pm",
        "57",
        "31",
        "38",
        "",
        "WSW",
        "5G10"
      ],
      [
        "Jul 3, 9:00 pm",
        "58",
        "33",
        "39",
        "",
        "SE",
        "3G11"
      ],
      [
        "Jul 3, 8:00 pm",
        "59",
        "30",
        "33",
        "",
        "NNW",
        "7G16"
      ],
      [
        "Jul 3, 7:00 pm",
        "60",
        "27",
        "29",
        "",
        "NW",
        "11G27"
      ],
      [
        "Jul 3, 6:00 pm",
        "60",
        "28",
        "30",
        "",
        "NW",
        "12G25"
      ],
      [
        "Jul 3, 5:00 pm",
        "60",
        "31",
        "33",
        "",
        "NW",
        "11G26"
      ],
      [
        "Jul 3, 4:00 pm",
        "60",
        "33",
        "36",
        "",
        "NW",
        "7G19"
      ]
    ]
  },
  "url": "https://www.weather.gov/wrh/timeseries?site=YCAMS&hours=168&units=english&chart=on&headers=on&obs=tabular&hourly=false&pview=full&font=12&plot="
}