{
  "station_id": "YCAMS",
  "station_name": "American Spirit",
  "timestamp": "2026-01-28T05:25:15.128864",
  "data": {
    "headers": [
      "Date/Time\u00a0(L)",
      "Temp.\u00a0(\u00b0F)",
      "DewPoint(\u00b0F)",
      "RelativeHumidity(%)",
      "WindChill(\u00b0F)",
      "WindDirection",
      "WindSpeed(mph)"
    ],
    "rows": [
      [
        "1 27",
        "2200",
        "8",
        "W - 267",
        "18",
        "24",
        "55"
      ],
      [
        "1 27",
        "2100",
        "5",
        "NW - 298",
        "15",
        "23",
        "58"
      ],
      [
        "1 27",
        "2000",
        "8",
        "W - 269",
        "17",
        "23",
        "61"
      ],
      [
        "1 27",
        "1900",
        "4",
        "NW - 321",
        "11",
        "23",
        "62"
      ],
      [
        "1 27",
        "1800",
        "5",
        "S - 198",
        "15",
        "23",
        "61"
      ],
      [
        "1 27",
        "1700",
        "5",
        "S - 165",
        "16",
        "24",
        "58"
      ],
      [
        "1 27",
        "1600",
        "6",
        "NW - 315",
        "17",
        "25",
        "55"
      ],
      [
        "1 27",
        "1500",
        "7",
        "SW - 242",
        "19",
        "26",
        "54"
      ],
      [
        "1 27",
        "1400",
        "10",
        "NW - 301",
        "20",
        "24",
        "55"
      ],
      [
        "1 27",
        "1300",
        "6",
        "NW - 301",
        "15",
        "24",
        "53"
      ],
      [
        "1 27",
        "1200",
        "9",
        "NW - 305",
        "18",
        "23",
        "56"
      ],
      [
        "1 27",
        "1100",
        "6",
        "W - 285",
        "15",
        "22",
        "53"
      ],
      [
        "1 27",
        "1000",
        "9",
        "NW - 299",
        "16",
        "20",
        "56"
      ],
      [
        "1 27",
        "900",
        "11",
        "NW - 299",
        "19",
        "19",
        "55"
      ],
      [
        "1 27",
        "800",
        "8",
        "NW - 307",
        "16",
        "19",
        "52"
      ],
      [
        "1 27",
        "700",
        "8",
        "NW - 326",
        "14",
        "19",
        "48"
      ],
      [
        "1 27",
        "600",
        "10",
        "N - 343",
        "25",
        "20",
        "43"
      ],
      [
        "1 27",
        "500",
        "7",
        "N - 1",
        "21",
        "19",
        "42"
      ],
      [
        "1 27",
        "400",
        "6",
        "E - 93",
        "15",
        "19",
        "44"
      ],
      [
        "1 27",
        "300",
        "5",
        "NE - 50",
        "18",
        "20",
        "45"
      ],
      [
        "1 27",
        "200",
        "8",
        "NW - 334",
        "23",
        "21",
        "46"
      ],
      [
        "1 27",
        "100",
        "6",
        "N - 19",
        "19",
        "21",
        "47"
      ],
      [
        "1 26",
        "2400",
        "10",
        "NW - 317",
        "23",
        "22",
        "38"
      ],
      [
        "1 26",
        "2300",
        "11",
        "NW - 306",
        "28",
        "21",
        "46"
      ],
      [
        "1 26",
        "2200",
        "7",
        "E - 92",
        "17",
        "20",
        "49"
      ],
      [
        "Jan 27, 10:00 pm",
        "24",
        "10",
        "55",
        "15",
        "W",
        "8G18"
      ],
      [
        "Jan 27, 9:00 pm",
        "23",
        "10",
        "58",
        "17",
        "WNW",
        "5G15"
      ],
      [
        "Jan 27, 8:00 pm",
        "23",
        "11",
        "61",
        "14",
        "W",
        "8G17"
      ],
      [
        "Jan 27, 7:00 pm",
        "23",
        "12",
        "62",
        "18",
        "NW",
        "4G11"
      ],
      [
        "Jan 27, 6:00 pm",
        "23",
        "11",
        "61",
        "17",
        "SSW",
        "5G15"
      ],
      [
        "Jan 27, 5:00 pm",
        "24",
        "11",
        "58",
        "18",
        "SSE",
        "5G16"
      ],
      [
        "Jan 27, 4:00 pm",
        "25",
        "11",
        "55",
        "18",
        "NW",
        "6G17"
      ],
      [
        "Jan 27, 3:00 pm",
        "26",
        "11",
        "54",
        "18",
        "WSW",
        "7G19"
      ],
      [
        "Jan 27, 2:00 pm",
        "24",
        "10",
        "55",
        "14",
        "WNW",
        "10G20"
      ],
      [
        "Jan 27, 1:00 pm",
        "24",
        "9",
        "53",
        "17",
        "WNW",
        "6G15"
      ],
      [
        "Jan 27, 12:00 pm",
        "23",
        "9",
        "56",
        "13",
        "NW",
        "9G18"
      ],
      [
        "Jan 27, 11:00 am",
        "22",
        "7",
        "53",
        "14",
        "WNW",
        "6G15"
      ],
      [
        "Jan 27, 10:00 am",
        "20",
        "7",
        "56",
        "10",
        "WNW",
        "9G16"
      ],
      [
        "Jan 27, 9:00 am",
        "19",
        "5",
        "55",
        "7",
        "WNW",
        "11G19"
      ],
      [
        "Jan 27, 8:00 am",
        "19",
        "4",
        "52",
        "9",
        "NW",
        "8G16"
      ],
      [
        "Jan 27, 7:00 am",
        "19",
        "2",
        "48",
        "9",
        "NW",
        "8G14"
      ],
      [
        "Jan 27, 6:00 am",
        "20",
        "1",
        "43",
        "9",
        "NNW",
        "10G25"
      ],
      [
        "Jan 27, 5:00 am",
        "19",
        "-1",
        "42",
        "10",
        "N",
        "7G21"
      ],
      [
        "Jan 27, 4:00 am",
        "19",
        "0",
        "44",
        "11",
        "E",
        "6G15"
      ],
      [
        "Jan 27, 3:00 am",
        "20",
        "2",
        "45",
        "13",
        "NE",
        "5G18"
      ],
      [
        "Jan 27, 2:00 am",
        "21",
        "3",
        "46",
        "11",
        "NNW",
        "8G23"
      ],
      [
        "Jan 27, 1:00 am",
        "21",
        "4",
        "47",
        "13",
        "NNE",
        "6G19"
      ],
      [
        "Jan 27, 12:00 am",
        "22",
        "0",
        "38",
        "11",
        "NW",
        "10G23"
      ],
      [
        "Jan 26, 11:00 pm",
        "21",
        "3",
        "46",
        "10",
        "NW",
        "11G28"
      ],
      [
        "Jan 26, 10:00 pm",
        "20",
        "4",
        "49",
        "11",
        "E",
        "7G17"
      ],
      [
        "Jan 26, 9:00 pm",
        "20",
        "3",
        "47",
        "11",
        "E",
        "7G21"
      ],
      [
        "Jan 26, 8:00 pm",
        "21",
        "-1",
        "38",
        "13",
        "NNW",
        "6G24"
      ],
      [
        "Jan 26, 7:00 pm",
        "22",
        "-6",
        "29",
        "13",
        "NNW",
        "7G22"
      ],
      [
        "Jan 26, 6:00 pm",
        "21",
        "-6",
        "29",
        "12",
        "N",
        "7G22"
      ],
      [
        "Jan 26, 5:00 pm",
        "21",
        "-7",
        "28",
        "11",
        "ENE",
        "8G20"
      ],
      [
        "Jan 26, 4:00 pm",
        "22",
        "-9",
        "25",
        "13",
        "E",
        "7G15"
      ],
      [
        "Jan 26, 3:00 pm",
        "22",
        "-9",
        "25",
        "14",
        "E",
        "6G22"
      ],
      [
        "Jan 26, 2:00 pm",
        "23",
        "-10",
        "22",
        "17",
        "NE",
        "5G16"
      ],
      [
        "Jan 26, 1:00 pm",
        "22",
        "-9",
        "24",
        "15",
        "E",
        "5G16"
      ],
      [
        "Jan 26, 12:00 pm",
        "21",
        "-10",
        "24",
        "15",
        "NE",
        "4G10"
      ],
      [
        "Jan 26, 11:00 am",
        "20",
        "-10",
        "26",
        "16",
        "NE",
        "3G9"
      ],
      [
        "Jan 26, 10:00 am",
        "18",
        "-11",
        "27",
        "12",
        "N",
        "4G15"
      ],
      [
        "Jan 26, 9:00 am",
        "16",
        "-11",
        "29",
        "8",
        "NNW",
        "5G17"
      ],
      [
        "Jan 26, 8:00 am",
        "14",
        "-11",
        "31",
        "7",
        "NW",
        "4G14"
      ],
      [
        "Jan 26, 7:00 am",
        "14",
        "-10",
        "33",
        "7",
        "N",
        "4G17"
      ],
      [
        "Jan 26, 6:00 am",
        "13",
        "-7",
        "39",
        "8",
        "ESE",
        "3G8"
      ],
      [
        "Jan 26, 5:00 am",
        "13",
        "-10",
        "35",
        "6",
        "ENE",
        "4G13"
      ],
      [
        "Jan 26, 4:00 am",
        "14",
        "-12",
        "30",
        "7",
        "ENE",
        "4G14"
      ],
      [
        "Jan 26, 3:00 am",
        "13",
        "-17",
        "24",
        "6",
        "ENE",
        "4G15"
      ],
      [
        "Jan 26, 2:00 am",
        "13",
        "-19",
        "22",
        "4",
        "N",
        "6G16"
      ],
      [
        "Jan 26, 1:00 am",
        "12",
        "-22",
        "19",
        "",
        "E",
        "2G9"
      ],
      [
        "Jan 26, 12:00 am",
        "12",
        "-23",
        "18",
        "7",
        "ESE",
        "3G9"
      ],
      [
        "Jan 25, 11:00 pm",
        "12",
        "-22",
        "19",
        "1",
        "W",
        "8G19"
      ],
      [
        "Jan 25, 10:00 pm",
        "11",
        "-21",
        "22",
        "0",
        "WNW",
        "7G17"
      ],
      [
        "Jan 25, 9:00 pm",
        "11",
        "-21",
        "22",
        "-2",
        "W",
        "9G20"
      ],
      [
        "Jan 25, 8:00 pm",
        "9",
        "-20",
        "25",
        "-1",
        "W",
        "6G18"
      ],
      [
        "Jan 25, 7:00 pm",
        "9",
        "-19",
        "26",
        "0",
        "W",
        "5G14"
      ],
      [
        "Jan 25, 6:00 pm",
        "7",
        "-15",
        "35",
        "-7",
        "WSW",
        "10G18"
      ],
      [
        "Jan 25, 5:00 pm",
        "6",
        "-13",
        "40",
        "-7",
        "WNW",
        "8G16"
      ],
      [
        "Jan 25, 4:00 pm",
        "7",
        "-21",
        "25",
        "-10",
        "WNW",
        "14G21"
      ],
      [
        "Jan 25, 3:00 pm",
        "6",
        "-20",
        "28",
        "-12",
        "WNW",
        "16G23"
      ],
      [
        "Jan 25, 2:00 pm",
        "5",
        "-20",
        "30",
        "-12",
        "W",
        "13G22"
      ],
      [
        "Jan 25, 1:00 pm",
        "3",
        "-15",
        "43",
        "-13",
        "WNW",
        "11G22"
      ],
      [
        "Jan 25, 12:00 pm",
        "1",
        "-13",
        "52",
        "-13",
        "WNW",
        "8G22"
      ],
      [
        "Jan 25, 11:00 am",
        "-1",
        "-9",
        "69",
        "-23",
        "NW",
        "20G30"
      ],
      [
        "Jan 25, 10:00 am",
        "-2",
        "-8",
        "75",
        "-24",
        "NW",
        "18G30"
      ],
      [
        "Jan 25, 9:00 am",
        "-3",
        "-8",
        "79",
        "-27",
        "NW",
        "23G36"
      ],
      [
        "Jan 25, 8:00 am",
        "-2",
        "-6",
        "81",
        "-26",
        "NW",
        "23G36"
      ],
      [
        "Jan 25, 7:00 am",
        "-1",
        "-6",
        "80",
        "-26",
        "NNW",
        "26G40"
      ],
      [
        "Jan 25, 6:00 am",
        "0",
        "-4",
        "84",
        "-25",
        "NNW",
        "27G40"
      ],
      [
        "Jan 25, 5:00 am",
        "0",
        "-4",
        "84",
        "-25",
        "NNW",
        "27G37"
      ],
      [
        "Jan 25, 4:00 am",
        "0",
        "-4",
        "84",
        "-22",
        "NNW",
        "21G32"
      ],
      [
        "Jan 25, 3:00 am",
        "0",
        "-4",
        "84",
        "-20",
        "NW",
        "16G24"
      ],
      [
        "Jan 25, 2:00 am",
        "1",
        "-3",
        "84",
        "-17",
        "NW",
        "13G18"
      ],
      [
        "Jan 25, 1:00 am",
        "2",
        "-2",
        "84",
        "-12",
        "NW",
        "8G17"
      ],
      [
        "Jan 25, 12:00 am",
        "2",
        "-2",
        "84",
        "-12",
        "NW",
        "8G14"
      ],
      [
        "Jan 24, 11:00 pm",
        "2",
        "-3",
        "81",
        "-9",
        "WNW",
        "6G14"
      ],
      [
        "Jan 24, 10:00 pm",
        "3",
        "-2",
        "79",
        "-9",
        "NW",
        "7G13"
      ],
      [
        "Jan 24, 9:00 pm",
        "3",
        "-2",
        "80",
        "-8",
        "NW",
        "6G16"
      ],
      [
        "Jan 24, 8:00 pm",
        "3",
        "-3",
        "76",
        "-12",
        "NW",
        "10G21"
      ],
      [
        "Jan 24, 7:00 pm",
        "2",
        "-4",
        "77",
        "-12",
        "WNW",
        "8G14"
      ],
      [
        "Jan 24, 6:00 pm",
        "3",
        "-2",
        "78",
        "-14",
        "WNW",
        "12G17"
      ],
      [
        "Jan 24, 5:00 pm",
        "4",
        "-3",
        "73",
        "-11",
        "WNW",
        "10G18"
      ],
      [
        "Jan 24, 4:00 pm",
        "3",
        "-2",
        "79",
        "-14",
        "NW",
        "12G17"
      ],
      [
        "Jan 24, 3:00 pm",
        "4",
        "-2",
        "77",
        "-12",
        "NW",
        "12G17"
      ],
      [
        "Jan 24, 2:00 pm",
        "5",
        "-5",
        "64",
        "-8",
        "WNW",
        "8G14"
      ],
      [
        "Jan 24, 1:00 pm",
        "3",
        "-5",
        "69",
        "-12",
        "NW",
        "10G15"
      ],
      [
        "Jan 24, 12:00 pm",
        "2",
        "-3",
        "79",
        "-16",
        "NW",
        "14G19"
      ],
      [
        "Jan 24, 11:00 am",
        "2",
        "-4",
        "77",
        "-13",
        "NW",
        "9G18"
      ],
      [
        "Jan 24, 10:00 am",
        "2",
        "-6",
        "68",
        "-13",
        "NW",
        "10G16"
      ],
      [
        "Jan 24, 9:00 am",
        "2",
        "-10",
        "57",
        "-13",
        "NW",
        "9G15"
      ],
      [
        "Jan 24, 8:00 am",
        "0",
        "-11",
        "59",
        "-19",
        "NW",
        "14G19"
      ],
      [
        "Jan 24, 7:00 am",
        "0",
        "-12",
        "55",
        "-19",
        "NW",
        "15G22"
      ],
      [
        "Jan 24, 6:00 am",
        "0",
        "-11",
        "58",
        "-18",
        "WNW",
        "13G18"
      ],
      [
        "Jan 24, 5:00 am",
        "0",
        "-16",
        "46",
        "-19",
        "NW",
        "14G22"
      ],
      [
        "Jan 24, 4:00 am",
        "0",
        "-16",
        "45",
        "-21",
        "NW",
        "17G23"
      ],
      [
        "Jan 24, 3:00 am",
        "0",
        "-16",
        "45",
        "-17",
        "WNW",
        "12G19"
      ],
      [
        "Jan 24, 2:00 am",
        "-3",
        "-15",
        "56",
        "-17",
        "NW",
        "7G16"
      ],
      [
        "Jan 24, 1:00 am",
        "-3",
        "-16",
        "53",
        "-15",
        "NW",
        "6G15"
      ],
      [
        "Jan 24, 12:00 am",
        "-3",
        "-16",
        "53",
        "-18",
        "NW",
        "8G15"
      ],
      [
        "Jan 23, 11:00 pm",
        "-4",
        "-10",
        "75",
        "",
        "NNW",
        "2G8"
      ],
      [
        "Jan 23, 10:00 pm",
        "-2",
        "-13",
        "58",
        "-20",
        "NW",
        "12G20"
      ],
      [
        "Jan 23, 9:00 pm",
        "-2",
        "-10",
        "68",
        "-20",
        "WNW",
        "12G19"
      ],
      [
        "Jan 23, 8:00 pm",
        "-3",
        "-8",
        "80",
        "-17",
        "NW",
        "7G12"
      ],
      [
        "Jan 23, 7:00 pm",
        "-1",
        "-6",
        "79",
        "-13",
        "NW",
        "6G14"
      ],
      [
        "Jan 23, 6:00 pm",
        "0",
        "-4",
        "81",
        "-12",
        "WNW",
        "6G15"
      ],
      [
        "Jan 23, 5:00 pm",
        "0",
        "-4",
        "83",
        "-13",
        "W",
        "7G18"
      ],
      [
        "Jan 23, 4:00 pm",
        "2",
        "-2",
        "82",
        "-15",
        "W",
        "12G18"
      ],
      [
        "Jan 23, 3:00 pm",
        "3",
        "-1",
        "82",
        "-14",
        "W",
        "13G21"
      ],
      [
        "Jan 23, 2:00 pm",
        "5",
        "0",
        "81",
        "-12",
        "WNW",
        "13G20"
      ],
      [
        "Jan 23, 1:00 pm",
        "6",
        "1",
        "80",
        "-5",
        "NW",
        "6G12"
      ],
      [
        "Jan 23, 12:00 pm",
        "6",
        "1",
        "80",
        "-2",
        "NNW",
        "4G11"
      ],
      [
        "Jan 23, 11:00 am",
        "7",
        "2",
        "79",
        "1",
        "NNW",
        "3G12"
      ],
      [
        "Jan 23, 10:00 am",
        "7",
        "3",
        "82",
        "-1",
        "NNW",
        "4G14"
      ],
      [
        "Jan 23, 9:00 am",
        "8",
        "5",
        "86",
        "-4",
        "WNW",
        "8G12"
      ],
      [
        "Jan 23, 8:00 am",
        "6",
        "3",
        "87",
        "-6",
        "NW",
        "7G11"
      ],
      [
        "Jan 23, 7:00 am",
        "5",
        "2",
        "86",
        "-3",
        "NW",
        "4G10"
      ],
      [
        "Jan 23, 6:00 am",
        "4",
        "0",
        "85",
        "",
        "WSW",
        "2G6"
      ],
      [
        "Jan 23, 5:00 am",
        "3",
        "-1",
        "85",
        "",
        "S",
        "1G4"
      ],
      [
        "Jan 23, 4:00 am",
        "3",
        "-1",
        "85",
        "",
        "W",
        "1G3"
      ],
      [
        "Jan 23, 3:00 am",
        "4",
        "0",
        "85",
        "",
        "SE",
        "0G3"
      ],
      [
        "Jan 23, 2:00 am",
        "5",
        "2",
        "86",
        "",
        "ESE",
        "0G3"
      ],
      [
        "Jan 23, 1:00 am",
        "6",
        "3",
        "86",
        "",
        "E",
        "0G3"
      ],
      [
        "Jan 23, 12:00 am",
        "5",
        "2",
        "87",
        "",
        "SE",
        "2G6"
      ],
      [
        "Jan 22, 11:00 pm",
        "5",
        "2",
        "88",
        "",
        "WNW",
        "2G4"
      ],
      [
        "Jan 22, 10:00 pm",
        "8",
        "5",
        "86",
        "",
        "NNE",
        "1G3"
      ],
      [
        "Jan 22, 9:00 pm",
        "13",
        "4",
        "67",
        "",
        "ESE",
        "0G6"
      ],
      [
        "Jan 22, 8:00 pm",
        "16",
        "4",
        "59",
        "",
        "NE",
        "1G4"
      ],
      [
        "Jan 22, 7:00 pm",
        "19",
        "-1",
        "41",
        "11",
        "NNW",
        "6G12"
      ],
      [
        "Jan 22, 6:00 pm",
        "21",
        "-2",
        "36",
        "12",
        "NNW",
        "7G21"
      ],
      [
        "Jan 22, 5:00 pm",
        "22",
        "-1",
        "36",
        "11",
        "NW",
        "10G21"
      ],
      [
        "Jan 22, 4:00 pm",
        "22",
        "-4",
        "32",
        "13",
        "NW",
        "8G19"
      ],
      [
        "Jan 22, 3:00 pm",
        "22",
        "-5",
        "30",
        "13",
        "WNW",
        "8G23"
      ],
      [
        "Jan 22, 2:00 pm",
        "22",
        "-9",
        "25",
        "12",
        "WNW",
        "9G18"
      ],
      [
        "Jan 22, 1:00 pm",
        "22",
        "-11",
        "22",
        "13",
        "WNW",
        "8G17"
      ],
      [
        "Jan 22, 12:00 pm",
        "22",
        "-10",
        "23",
        "14",
        "WNW",
        "6G18"
      ],
      [
        "Jan 22, 11:00 am",
        "21",
        "-9",
        "26",
        "17",
        "N",
        "3G13"
      ],
      [
        "Jan 22, 10:00 am",
        "20",
        "-10",
        "26",
        "12",
        "NNW",
        "6G14"
      ],
      [
        "Jan 22, 9:00 am",
        "19",
        "-11",
        "25",
        "8",
        "NW",
        "9G18"
      ],
      [
        "Jan 22, 8:00 am",
        "19",
        "-11",
        "25",
        "10",
        "WNW",
        "7G15"
      ],
      [
        "Jan 22, 7:00 am",
        "19",
        "-11",
        "25",
        "8",
        "NW",
        "9G23"
      ],
      [
        "Jan 22, 6:00 am",
        "20",
        "-10",
        "26",
        "11",
        "WNW",
        "7G15"
      ],
      [
        "Jan 22, 5:00 am",
        "19",
        "-8",
        "29",
        "10",
        "WNW",
        "7G16"
      ],
      [
        "Jan 22, 4:00 am",
        "20",
        "-7",
        "30",
        "10",
        "WNW",
        "8G16"
      ],
      [
        "Jan 22, 3:00 am",
        "20",
        "-7",
        "30",
        "10",
        "WNW",
        "8G17"
      ],
      [
        "Jan 22, 2:00 am",
        "21",
        "-6",
        "30",
        "11",
        "WNW",
        "8G17"
      ],
      [
        "Jan 22, 1:00 am",
        "21",
        "-6",
        "30",
        "13",
        "WNW",
        "6G18"
      ],
      [
        "Jan 22, 12:00 am",
        "22",
        "-5",
        "30",
        "13",
        "W",
        "7G17"
      ],
      [
        "Jan 21, 11:00 pm",
        "22",
        "-6",
        "29",
        "12",
        "WNW",
        "9G20"
      ],
      [
        "Jan 21, 10:00 pm",
        "22",
        "-5",
        "30",
        "11",
        "WNW",
        "10G21"
      ],
      [
        "Jan 21, 9:00 pm",
        "22",
        "-5",
        "30",
        "12",
        "WNW",
        "9G22"
      ],
      [
        "Jan 21, 8:00 pm",
        "23",
        "-3",
        "31",
        "15",
        "W",
        "7G21"
      ],
      [
        "Jan 21, 7:00 pm",
        "23",
        "-3",
        "31",
        "16",
        "WNW",
        "6G21"
      ],
      [
        "Jan 21, 6:00 pm",
        "23",
        "-4",
        "30",
        "17",
        "N",
        "5G15"
      ],
      [
        "Jan 21, 5:00 pm",
        "24",
        "-4",
        "29",
        "15",
        "NW",
        "8G19"
      ],
      [
        "Jan 21, 4:00 pm",
        "24",
        "-4",
        "29",
        "15",
        "WNW",
        "8G20"
      ],
      [
        "Jan 21, 3:00 pm",
        "24",
        "-5",
        "28",
        "14",
        "WNW",
        "10G26"
      ],
      [
        "Jan 21, 2:00 pm",
        "24",
        "-4",
        "29",
        "12",
        "NW",
        "13G27"
      ],
      [
        "Jan 21, 1:00 pm",
        "23",
        "-5",
        "29",
        "12",
        "NW",
        "11G22"
      ],
      [
        "Jan 21, 12:00 pm",
        "23",
        "-5",
        "29",
        "13",
        "NW",
        "10G23"
      ],
      [
        "Jan 21, 11:00 am",
        "22",
        "-5",
        "30",
        "11",
        "WNW",
        "10G23"
      ],
      [
        "Jan 21, 10:00 am",
        "21",
        "-4",
        "32",
        "8",
        "NW",
        "14G32"
      ],
      [
        "Jan 21, 9:00 am",
        "21",
        "-3",
        "34",
        "6",
        "NW",
        "20G31"
      ],
      [
        "Jan 21, 8:00 am",
        "19",
        "-6",
        "33",
        "6",
        "NW",
        "13G27"
      ],
      [
        "Jan 21, 7:00 am",
        "18",
        "-6",
        "33",
        "4",
        "NW",
        "15G21"
      ],
      [
        "Jan 21, 6:00 am",
        "19",
        "-6",
        "33",
        "5",
        "WNW",
        "14G20"
      ],
      [
        "Jan 21, 5:00 am",
        "18",
        "-4",
        "37",
        "5",
        "NW",
        "13G22"
      ],
      [
        "Jan 21, 4:00 am",
        "20",
        "-6",
        "31",
        "6",
        "NW",
        "16G25"
      ],
      [
        "Jan 21, 3:00 am",
        "20",
        "-5",
        "33",
        "7",
        "NW",
        "14G24"
      ],
      [
        "Jan 21, 2:00 am",
        "21",
        "-6",
        "29",
        "6",
        "WNW",
        "20G33"
      ],
      [
        "Jan 21, 1:00 am",
        "21",
        "-6",
        "29",
        "7",
        "WNW",
        "16G28"
      ],
      [
        "Jan 21, 12:00 am",
        "21",
        "-8",
        "27",
        "6",
        "WNW",
        "19G31"
      ],
      [
        "Jan 20, 11:00 pm",
        "21",
        "-10",
        "24",
        "5",
        "NW",
        "23G37"
      ]
    ]
  },
  "url": "https://www.weather.gov/wrh/timeseries?site=YCAMS&hours=168&units=english&chart=on&headers=on&obs=tabular&hourly=false&pview=full&font=12&plot=",
  "sources": [
    "mtavalanche",
    "weather.gov"
  ],
  "mtavalanche_url": "https://www.mtavalanche.com/weather/stations/american-spirit-station"
}