{
  "station_id": "YCAND",
  "station_name": "Andesite",
  "timestamp": "2025-12-23T03:23:55.557159",
  "data": {
    "headers": [
      "Date/Time\u00a0(L)",
      "Temp.\u00a0(\u00b0F)",
      "WindChill(\u00b0F)",
      "WindDirection",
      "WindSpeed(mph)",
      "SnowDepth(in)",
      "Snowfall3 hour(in)",
      "Snowfall6 Hour(in)",
      "Snowfall24 Hour(in)"
    ],
    "rows": [
      [
        "12 22",
        "2000",
        "15",
        "S - 174",
        "25",
        "29",
        "-6999",
        "27.3"
      ],
      [
        "12 22",
        "1900",
        "13",
        "S - 170",
        "25",
        "29",
        "-6999",
        "27.0"
      ],
      [
        "12 22",
        "1800",
        "11",
        "S - 179",
        "24",
        "28",
        "-6999",
        "27.0"
      ],
      [
        "12 22",
        "1700",
        "6",
        "S - 190",
        "17",
        "28",
        "-6999",
        "27.1"
      ],
      [
        "12 22",
        "1600",
        "6",
        "S - 198",
        "19",
        "29",
        "-6999",
        "27.1"
      ],
      [
        "12 22",
        "1500",
        "4",
        "SW - 224",
        "15",
        "29",
        "-6999",
        "27.2"
      ],
      [
        "12 22",
        "1400",
        "7",
        "W - 258",
        "23",
        "28",
        "-6999",
        "27.2"
      ],
      [
        "12 22",
        "1300",
        "8",
        "W - 250",
        "24",
        "28",
        "-6999",
        "27.3"
      ],
      [
        "12 22",
        "1200",
        "10",
        "W - 259",
        "30",
        "27",
        "-6999",
        "76.5"
      ],
      [
        "12 22",
        "1100",
        "13",
        "W - 267",
        "34",
        "27",
        "-6999",
        "27.0"
      ],
      [
        "12 22",
        "1000",
        "10",
        "S - 193",
        "31",
        "31",
        "-6999",
        "76.4"
      ],
      [
        "12 22",
        "900",
        "9",
        "S - 186",
        "26",
        "30",
        "-6999",
        "76.7"
      ],
      [
        "12 22",
        "800",
        "10",
        "S - 183",
        "23",
        "32",
        "-6999",
        "25.1"
      ],
      [
        "12 22",
        "700",
        "10",
        "S - 182",
        "27",
        "32",
        "-6999",
        "25.1"
      ],
      [
        "12 22",
        "600",
        "12",
        "S - 181",
        "32",
        "31",
        "-6999",
        "25.2"
      ],
      [
        "12 22",
        "500",
        "12",
        "S - 183",
        "28",
        "31",
        "-6999",
        "25.3"
      ],
      [
        "12 22",
        "400",
        "13",
        "S - 179",
        "28",
        "32",
        "-6999",
        "24.7"
      ],
      [
        "12 22",
        "300",
        "11",
        "S - 175",
        "25",
        "32",
        "-6999",
        "24.2"
      ],
      [
        "12 22",
        "200",
        "12",
        "S - 175",
        "25",
        "32",
        "-6999",
        "24.3"
      ],
      [
        "12 22",
        "100",
        "12",
        "S - 176",
        "24",
        "32",
        "-6999",
        "24.3"
      ],
      [
        "12 21",
        "2400",
        "12",
        "S - 178",
        "22",
        "32",
        "-6999",
        "24.3"
      ],
      [
        "12 21",
        "2300",
        "11",
        "S - 175",
        "24",
        "31",
        "-6999",
        "24.2"
      ],
      [
        "12 21",
        "2200",
        "13",
        "S - 177",
        "23",
        "31",
        "-6999",
        "24.1"
      ],
      [
        "12 21",
        "2100",
        "14",
        "S - 177",
        "25",
        "31",
        "-6999",
        "24.0"
      ],
      [
        "12 21",
        "2000",
        "12",
        "S - 180",
        "23",
        "30",
        "-6999",
        "24.5"
      ],
      [
        "Dec 22, 8:00 pm",
        "29",
        "18",
        "S",
        "15G25",
        "27.3",
        "0.2",
        "0.1",
        "2.8"
      ],
      [
        "Dec 22, 7:00 pm",
        "29",
        "19",
        "S",
        "13G25",
        "27.0",
        "0.0",
        "0.0",
        "2.6"
      ],
      [
        "Dec 22, 6:00 pm",
        "28",
        "18",
        "S",
        "11G24",
        "27.0",
        "0.0",
        "0.0",
        "2.8"
      ],
      [
        "Dec 22, 5:00 pm",
        "28",
        "21",
        "S",
        "6G17",
        "27.1",
        "0.0",
        "0.1",
        "3.1"
      ],
      [
        "Dec 22, 4:00 pm",
        "29",
        "23",
        "SSW",
        "6G19",
        "27.1",
        "0.0",
        "0.0",
        "3.4"
      ],
      [
        "Dec 22, 3:00 pm",
        "29",
        "25",
        "SW",
        "4G15",
        "27.2",
        "0.0",
        "0.0",
        "4.0"
      ],
      [
        "Dec 22, 2:00 pm",
        "28",
        "21",
        "WSW",
        "7G23",
        "27.2",
        "0.2",
        "2.1",
        "4.4"
      ],
      [
        "Dec 22, 1:00 pm",
        "28",
        "20",
        "WSW",
        "8G24",
        "27.3",
        "0.0",
        "2.2",
        "4.8"
      ],
      [
        "Dec 22, 12:00 pm",
        "27",
        "18",
        "W",
        "10G30",
        "76.5",
        "0.0",
        "51.3",
        "54.7"
      ],
      [
        "Dec 22, 11:00 am",
        "27",
        "16",
        "W",
        "13G34",
        "27.0",
        "1.9",
        "1.7",
        "5.8"
      ],
      [
        "Dec 22, 10:00 am",
        "31",
        "22",
        "SSW",
        "10G31",
        "76.4",
        "51.3",
        "51.7",
        "55.8"
      ],
      [
        "Dec 22, 9:00 am",
        "30",
        "22",
        "S",
        "9G26",
        "76.7",
        "51.5",
        "52.5",
        "55.9"
      ],
      [
        "Dec 22, 8:00 am",
        "32",
        "24",
        "S",
        "10G23",
        "25.1",
        "0.0",
        "0.8",
        "4.3"
      ],
      [
        "Dec 22, 7:00 am",
        "32",
        "24",
        "S",
        "10G27",
        "25.1",
        "0.4",
        "0.8",
        "4.3"
      ],
      [
        "Dec 22, 6:00 am",
        "31",
        "22",
        "S",
        "12G32",
        "25.2",
        "1.0",
        "0.9",
        "4.4"
      ],
      [
        "Dec 22, 5:00 am",
        "31",
        "22",
        "S",
        "12G28",
        "25.3",
        "1.0",
        "1.1",
        "4.5"
      ],
      [
        "Dec 22, 4:00 am",
        "32",
        "22",
        "S",
        "13G28",
        "24.7",
        "0.4",
        "0.6",
        "3.9"
      ],
      [
        "Dec 22, 3:00 am",
        "32",
        "23",
        "S",
        "11G25",
        "24.2",
        "0.0",
        "0.2",
        "3.3"
      ],
      [
        "Dec 22, 2:00 am",
        "32",
        "23",
        "S",
        "12G25",
        "24.3",
        "0.1",
        "0.0",
        "3.4"
      ],
      [
        "Dec 22, 1:00 am",
        "32",
        "23",
        "S",
        "12G24",
        "24.3",
        "0.2",
        "0.0",
        "3.4"
      ],
      [
        "Dec 22, 12:00 am",
        "32",
        "23",
        "S",
        "12G22",
        "24.3",
        "0.3",
        "0.1",
        "3.5"
      ],
      [
        "Dec 21, 11:00 pm",
        "31",
        "22",
        "S",
        "11G24",
        "24.2",
        "0.0",
        "0.2",
        "3.3"
      ],
      [
        "Dec 21, 10:00 pm",
        "31",
        "21",
        "S",
        "13G23",
        "24.1",
        "0.0",
        "0.4",
        "3.2"
      ],
      [
        "Dec 21, 9:00 pm",
        "31",
        "21",
        "S",
        "14G25",
        "24.0",
        "0.0",
        "0.8",
        "3.1"
      ],
      [
        "Dec 21, 8:00 pm",
        "30",
        "20",
        "S",
        "12G23",
        "24.5",
        "0.5",
        "1.7",
        "3.7"
      ],
      [
        "Dec 21, 7:00 pm",
        "30",
        "20",
        "S",
        "13G28",
        "24.4",
        "0.7",
        "1.9",
        "3.6"
      ],
      [
        "Dec 21, 6:00 pm",
        "29",
        "20",
        "S",
        "10G25",
        "24.2",
        "1.0",
        "2.4",
        "3.4"
      ],
      [
        "Dec 21, 5:00 pm",
        "29",
        "19",
        "S",
        "12G25",
        "24.0",
        "1.2",
        "2.8",
        "3.3"
      ],
      [
        "Dec 21, 4:00 pm",
        "28",
        "19",
        "S",
        "10G24",
        "23.7",
        "1.2",
        "3.1",
        "3.1"
      ],
      [
        "Dec 21, 3:00 pm",
        "28",
        "18",
        "S",
        "11G22",
        "23.2",
        "1.4",
        "2.4",
        "2.7"
      ],
      [
        "Dec 21, 2:00 pm",
        "28",
        "18",
        "S",
        "12G23",
        "22.8",
        "1.6",
        "2.0",
        "2.2"
      ],
      [
        "Dec 21, 1:00 pm",
        "26",
        "16",
        "SSE",
        "10G21",
        "22.5",
        "1.9",
        "1.7",
        "1.9"
      ],
      [
        "Dec 21, 12:00 pm",
        "24",
        "16",
        "SSE",
        "7G19",
        "21.8",
        "1.0",
        "1.0",
        "0.6"
      ],
      [
        "Dec 21, 11:00 am",
        "24",
        "17",
        "SSE",
        "6G17",
        "21.2",
        "0.4",
        "0.4",
        "0.0"
      ],
      [
        "Dec 21, 10:00 am",
        "22",
        "18",
        "SSE",
        "3G10",
        "20.6",
        "0.0",
        "0.0",
        "0.0"
      ],
      [
        "Dec 21, 9:00 am",
        "22",
        "17",
        "SW",
        "4G15",
        "20.8",
        "0.0",
        "0.0",
        "0.0"
      ],
      [
        "Dec 21, 8:00 am",
        "21",
        "",
        "WSW",
        "2G6",
        "20.8",
        "0.0",
        "0.0",
        "0.0"
      ],
      [
        "Dec 21, 7:00 am",
        "21",
        "14",
        "SSW",
        "5G17",
        "20.8",
        "0.0",
        "0.0",
        "0.0"
      ],
      [
        "Dec 21, 6:00 am",
        "21",
        "13",
        "SSW",
        "6G19",
        "20.8",
        "0.0",
        "0.0",
        "0.0"
      ],
      [
        "Dec 21, 5:00 am",
        "20",
        "12",
        "SSW",
        "6G17",
        "20.8",
        "0.0",
        "0.0",
        "0.0"
      ],
      [
        "Dec 21, 4:00 am",
        "19",
        "13",
        "SSW",
        "4G16",
        "20.8",
        "0.0",
        "0.0",
        "0.0"
      ],
      [
        "Dec 21, 3:00 am",
        "18",
        "12",
        "S",
        "4G11",
        "20.9",
        "0.1",
        "0.0",
        "0.0"
      ],
      [
        "Dec 21, 2:00 am",
        "17",
        "11",
        "SSW",
        "4G16",
        "20.9",
        "0.0",
        "0.1",
        "0.0"
      ],
      [
        "Dec 21, 1:00 am",
        "17",
        "9",
        "SSW",
        "5G14",
        "20.9",
        "0.0",
        "0.1",
        "0.0"
      ],
      [
        "Dec 21, 12:00 am",
        "16",
        "7",
        "SSW",
        "6G16",
        "20.8",
        "0.0",
        "0.0",
        "0.0"
      ],
      [
        "Dec 20, 11:00 pm",
        "15",
        "8",
        "SW",
        "4G18",
        "20.9",
        "0.1",
        "0.2",
        "0.0"
      ],
      [
        "Dec 20, 10:00 pm",
        "14",
        "9",
        "SW",
        "3G14",
        "20.9",
        "0.1",
        "0.3",
        "0.0"
      ],
      [
        "Dec 20, 9:00 pm",
        "15",
        "6",
        "SW",
        "6G14",
        "20.9",
        "0.1",
        "0.4",
        "0.0"
      ],
      [
        "Dec 20, 8:00 pm",
        "15",
        "6",
        "SW",
        "6G12",
        "20.8",
        "0.1",
        "0.2",
        "0.0"
      ],
      [
        "Dec 20, 7:00 pm",
        "14",
        "5",
        "SSW",
        "6G14",
        "20.8",
        "0.2",
        "0.2",
        "0.0"
      ],
      [
        "Dec 20, 6:00 pm",
        "13",
        "5",
        "SW",
        "5G12",
        "20.8",
        "0.3",
        "0.0",
        "0.2"
      ],
      [
        "Dec 20, 5:00 pm",
        "14",
        "6",
        "W",
        "5G13",
        "20.7",
        "0.1",
        "0.0",
        "0.4"
      ],
      [
        "Dec 20, 4:00 pm",
        "16",
        "7",
        "SW",
        "6G17",
        "20.6",
        "0.0",
        "0.0",
        "0.4"
      ],
      [
        "Dec 20, 3:00 pm",
        "17",
        "9",
        "SW",
        "5G13",
        "20.5",
        "0.0",
        "0.0",
        "0.9"
      ],
      [
        "Dec 20, 2:00 pm",
        "16",
        "6",
        "W",
        "7G18",
        "20.6",
        "0.0",
        "0.0",
        "1.0"
      ],
      [
        "Dec 20, 1:00 pm",
        "16",
        "10",
        "SW",
        "4G13",
        "20.6",
        "0.0",
        "0.0",
        "1.0"
      ],
      [
        "Dec 20, 12:00 pm",
        "15",
        "8",
        "SSW",
        "4G11",
        "21.2",
        "0.2",
        "0.2",
        "0.8"
      ],
      [
        "Dec 20, 11:00 am",
        "13",
        "6",
        "SW",
        "4G10",
        "21.8",
        "0.8",
        "0.8",
        "0.5"
      ],
      [
        "Dec 20, 10:00 am",
        "12",
        "5",
        "W",
        "4G13",
        "21.7",
        "0.7",
        "0.6",
        "0.0"
      ],
      [
        "Dec 20, 9:00 am",
        "11",
        "1",
        "W",
        "6G15",
        "21.0",
        "0.0",
        "0.0",
        "0.0"
      ],
      [
        "Dec 20, 8:00 am",
        "10",
        "-3",
        "W",
        "9G18",
        "21.0",
        "0.0",
        "0.0",
        "0.0"
      ],
      [
        "Dec 20, 7:00 am",
        "10",
        "-3",
        "W",
        "9G23",
        "21.0",
        "0.0",
        "0.0",
        "0.0"
      ],
      [
        "Dec 20, 6:00 am",
        "11",
        "-1",
        "W",
        "8G25",
        "21.0",
        "0.0",
        "0.0",
        "0.0"
      ],
      [
        "Dec 20, 5:00 am",
        "11",
        "-1",
        "W",
        "8G17",
        "21.0",
        "0.0",
        "0.0",
        "0.0"
      ],
      [
        "Dec 20, 4:00 am",
        "11",
        "-1",
        "W",
        "8G18",
        "21.1",
        "0.0",
        "0.0",
        "0.0"
      ],
      [
        "Dec 20, 3:00 am",
        "11",
        "-1",
        "W",
        "8G19",
        "21.1",
        "0.0",
        "0.0",
        "0.0"
      ],
      [
        "Dec 20, 2:00 am",
        "11",
        "0",
        "W",
        "7G21",
        "21.0",
        "0.0",
        "0.0",
        "0.0"
      ],
      [
        "Dec 20, 1:00 am",
        "11",
        "-2",
        "W",
        "10G29",
        "21.2",
        "0.0",
        "0.1",
        "0.0"
      ],
      [
        "Dec 20, 12:00 am",
        "12",
        "-4",
        "W",
        "15G31",
        "21.4",
        "0.0",
        "0.8",
        "0.0"
      ],
      [
        "Dec 19, 11:00 pm",
        "12",
        "-4",
        "W",
        "15G33",
        "21.4",
        "0.1",
        "1.1",
        "0.0"
      ],
      [
        "Dec 19, 10:00 pm",
        "13",
        "-3",
        "W",
        "15G33",
        "21.9",
        "0.8",
        "1.7",
        "0.0"
      ],
      [
        "Dec 19, 9:00 pm",
        "14",
        "-2",
        "W",
        "17G43",
        "22.1",
        "1.5",
        "2.5",
        "0.0"
      ],
      [
        "Dec 19, 8:00 pm",
        "16",
        "3",
        "WNW",
        "11G29",
        "21.3",
        "1.0",
        "1.7",
        "0.0"
      ],
      [
        "Dec 19, 7:00 pm",
        "18",
        "4",
        "W",
        "15G32",
        "21.1",
        "0.9",
        "1.5",
        "0.0"
      ],
      [
        "Dec 19, 6:00 pm",
        "20",
        "7",
        "WNW",
        "13G24",
        "20.6",
        "1.0",
        "0.2",
        "0.0"
      ],
      [
        "Dec 19, 5:00 pm",
        "20",
        "8",
        "W",
        "12G23",
        "20.3",
        "0.7",
        "0.0",
        "0.0"
      ],
      [
        "Dec 19, 4:00 pm",
        "24",
        "14",
        "W",
        "10G22",
        "20.2",
        "0.6",
        "0.0",
        "0.0"
      ],
      [
        "Dec 19, 3:00 pm",
        "30",
        "20",
        "SSW",
        "13G34",
        "19.6",
        "0.0",
        "0.0",
        "0.0"
      ],
      [
        "Dec 19, 2:00 pm",
        "31",
        "21",
        "S",
        "13G28",
        "19.6",
        "0.0",
        "0.0",
        "0.0"
      ],
      [
        "Dec 19, 1:00 pm",
        "31",
        "20",
        "S",
        "15G44",
        "19.6",
        "0.0",
        "0.0",
        "0.0"
      ],
      [
        "Dec 19, 12:00 pm",
        "31",
        "21",
        "S",
        "14G34",
        "20.4",
        "0.0",
        "0.0",
        "0.0"
      ],
      [
        "Dec 19, 11:00 am",
        "30",
        "20",
        "S",
        "13G35",
        "21.3",
        "0.0",
        "0.0",
        "0.0"
      ],
      [
        "Dec 19, 10:00 am",
        "30",
        "20",
        "S",
        "13G33",
        "22.1",
        "0.0",
        "0.0",
        "0.0"
      ],
      [
        "Dec 19, 9:00 am",
        "29",
        "19",
        "S",
        "13G43",
        "22.4",
        "0.0",
        "0.0",
        "0.0"
      ],
      [
        "Dec 19, 8:00 am",
        "29",
        "19",
        "S",
        "13G28",
        "22.8",
        "0.0",
        "0.0",
        "3.1"
      ],
      [
        "Dec 19, 7:00 am",
        "29",
        "19",
        "S",
        "13G33",
        "23.0",
        "0.0",
        "0.0",
        "3.2"
      ],
      [
        "Dec 19, 6:00 am",
        "29",
        "18",
        "S",
        "15G36",
        "23.8",
        "0.6",
        "0.9",
        "4.0"
      ],
      [
        "Dec 19, 5:00 am",
        "28",
        "17",
        "S",
        "13G35",
        "24.6",
        "0.5",
        "1.6",
        "4.8"
      ],
      [
        "Dec 19, 4:00 am",
        "27",
        "16",
        "S",
        "14G32",
        "24.1",
        "0.1",
        "0.5",
        "4.2"
      ],
      [
        "Dec 19, 3:00 am",
        "26",
        "14",
        "S",
        "15G29",
        "23.2",
        "0.3",
        "0.0",
        "3.3"
      ],
      [
        "Dec 19, 2:00 am",
        "27",
        "15",
        "S",
        "16G33",
        "24.1",
        "1.1",
        "0.2",
        "4.2"
      ],
      [
        "Dec 19, 1:00 am",
        "24",
        "14",
        "S",
        "10G25",
        "24.0",
        "0.4",
        "0.4",
        "4.1"
      ],
      [
        "Dec 19, 12:00 am",
        "22",
        "13",
        "SSE",
        "7G24",
        "22.9",
        "0.0",
        "0.0",
        "2.9"
      ],
      [
        "Dec 18, 11:00 pm",
        "23",
        "14",
        "SSE",
        "8G20",
        "23.0",
        "0.0",
        "0.2",
        "3.0"
      ],
      [
        "Dec 18, 10:00 pm",
        "23",
        "14",
        "S",
        "8G21",
        "23.6",
        "0.0",
        "0.0",
        "3.7"
      ],
      [
        "Dec 18, 9:00 pm",
        "22",
        "14",
        "SSW",
        "6G17",
        "23.7",
        "0.0",
        "0.0",
        "3.6"
      ],
      [
        "Dec 18, 8:00 pm",
        "21",
        "11",
        "S",
        "9G18",
        "23.9",
        "1.1",
        "1.2",
        "3.8"
      ],
      [
        "Dec 18, 7:00 pm",
        "20",
        "11",
        "S",
        "7G17",
        "23.6",
        "0.0",
        "2.3",
        "4.0"
      ],
      [
        "Dec 18, 6:00 pm",
        "19",
        "8",
        "S",
        "10G20",
        "23.8",
        "0.0",
        "0.0",
        "4.7"
      ],
      [
        "Dec 18, 5:00 pm",
        "18",
        "5",
        "S",
        "12G25",
        "22.8",
        "0.1",
        "0.0",
        "5.2"
      ],
      [
        "Dec 18, 4:00 pm",
        "17",
        "3",
        "S",
        "13G22",
        "76.5",
        "55.2",
        "0.0",
        "60.3"
      ],
      [
        "Dec 18, 3:00 pm",
        "16",
        "3",
        "SSE",
        "11G20",
        "60.8",
        "0.0",
        "0.0",
        "45.0"
      ],
      [
        "Dec 18, 2:00 pm",
        "15",
        "1",
        "S",
        "13G29",
        "22.7",
        "0.0",
        "3.0",
        "6.9"
      ],
      [
        "Dec 18, 1:00 pm",
        "15",
        "5",
        "SSE",
        "7G18",
        "21.3",
        "0.0",
        "1.5",
        "5.3"
      ],
      [
        "Dec 18, 12:00 pm",
        "14",
        "4",
        "S",
        "7G18",
        "76.4",
        "0.0",
        "56.6",
        "60.2"
      ],
      [
        "Dec 18, 11:00 am",
        "14",
        "6",
        "S",
        "5G13",
        "77.0",
        "57.3",
        "57.2",
        "61.2"
      ],
      [
        "Dec 18, 10:00 am",
        "15",
        "7",
        "SSW",
        "5G17",
        "77.0",
        "57.2",
        "57.1",
        "0.8"
      ],
      [
        "Dec 18, 9:00 am",
        "13",
        "3",
        "S",
        "7G16",
        "76.9",
        "57.1",
        "57.0",
        "0.8"
      ],
      [
        "Dec 18, 8:00 am",
        "11",
        "6",
        "SW",
        "3G9",
        "19.7",
        "0.0",
        "0.0",
        "0.0"
      ],
      [
        "Dec 18, 7:00 am",
        "11",
        "",
        "ESE",
        "2G9",
        "19.8",
        "0.0",
        "0.0",
        "5.6"
      ],
      [
        "Dec 18, 6:00 am",
        "10",
        "",
        "SSE",
        "2G6",
        "19.8",
        "0.0",
        "0.0",
        "5.9"
      ],
      [
        "Dec 18, 5:00 am",
        "10",
        "3",
        "SW",
        "4G12",
        "19.8",
        "0.0",
        "0.0",
        "5.9"
      ],
      [
        "Dec 18, 4:00 am",
        "10",
        "0",
        "W",
        "6G14",
        "19.9",
        "0.0",
        "0.0",
        "6.0"
      ],
      [
        "Dec 18, 3:00 am",
        "11",
        "0",
        "W",
        "7G22",
        "19.9",
        "0.0",
        "0.0",
        "6.0"
      ],
      [
        "Dec 18, 2:00 am",
        "11",
        "-4",
        "W",
        "12G25",
        "19.9",
        "0.0",
        "0.0",
        "5.9"
      ],
      [
        "Dec 18, 1:00 am",
        "11",
        "-4",
        "W",
        "13G27",
        "19.9",
        "0.0",
        "0.3",
        "5.8"
      ],
      [
        "Dec 18, 12:00 am",
        "12",
        "-2",
        "W",
        "11G32",
        "20.0",
        "0.0",
        "0.9",
        "5.9"
      ],
      [
        "Dec 17, 11:00 pm",
        "12",
        "-2",
        "W",
        "11G31",
        "20.0",
        "0.0",
        "2.4",
        "6.0"
      ],
      [
        "Dec 17, 10:00 pm",
        "12",
        "1",
        "W",
        "8G17",
        "19.9",
        "0.3",
        "3.7",
        "5.9"
      ],
      [
        "Dec 17, 9:00 pm",
        "12",
        "-4",
        "W",
        "14G31",
        "20.1",
        "1.0",
        "4.3",
        "6.1"
      ],
      [
        "Dec 17, 8:00 pm",
        "12",
        "-5",
        "W",
        "17G37",
        "20.1",
        "2.5",
        "4.3",
        "6.1"
      ],
      [
        "Dec 17, 7:00 pm",
        "13",
        "-4",
        "W",
        "17G42",
        "19.6",
        "3.4",
        "3.6",
        "5.7"
      ],
      [
        "Dec 17, 6:00 pm",
        "13",
        "-6",
        "W",
        "22G44",
        "19.1",
        "3.3",
        "2.9",
        "5.2"
      ],
      [
        "Dec 17, 5:00 pm",
        "14",
        "-5",
        "W",
        "25G56",
        "17.6",
        "1.8",
        "1.8",
        "0.0"
      ],
      [
        "Dec 17, 4:00 pm",
        "16",
        "-3",
        "W",
        "25G55",
        "16.2",
        "0.2",
        "0.0",
        "0.0"
      ],
      [
        "Dec 17, 3:00 pm",
        "19",
        "4",
        "W",
        "17G40",
        "15.8",
        "0.0",
        "0.0",
        "0.0"
      ],
      [
        "Dec 17, 2:00 pm",
        "20",
        "4",
        "W",
        "22G48",
        "15.8",
        "0.0",
        "0.0",
        "1.0"
      ],
      [
        "Dec 17, 1:00 pm",
        "24",
        "7",
        "W",
        "27G54",
        "16.0",
        "0.0",
        "1.8",
        "0.0"
      ],
      [
        "Dec 17, 12:00 pm",
        "27",
        "15",
        "W",
        "16G37",
        "16.2",
        "0.0",
        "2.3",
        "0.0"
      ],
      [
        "Dec 17, 11:00 am",
        "29",
        "20",
        "WSW",
        "10G47",
        "15.8",
        "0.0",
        "1.9",
        "0.0"
      ],
      [
        "Dec 17, 10:00 am",
        "30",
        "20",
        "S",
        "13G37",
        "76.2",
        "62.0",
        "62.3",
        "0.0"
      ],
      [
        "Dec 17, 9:00 am",
        "31",
        "20",
        "S",
        "17G42",
        "76.1",
        "62.2",
        "62.2",
        "0.2"
      ],
      [
        "Dec 17, 8:00 am",
        "32",
        "21",
        "S",
        "16G42",
        "58.1",
        "44.2",
        "44.1",
        "44.1"
      ],
      [
        "Dec 17, 7:00 am",
        "31",
        "20",
        "S",
        "16G33",
        "14.2",
        "0.3",
        "0.1",
        "0.1"
      ],
      [
        "Dec 17, 6:00 am",
        "31",
        "20",
        "S",
        "17G32",
        "13.9",
        "0.0",
        "0.0",
        "0.0"
      ],
      [
        "Dec 17, 5:00 am",
        "31",
        "19",
        "S",
        "18G34",
        "13.9",
        "0.0",
        "0.0",
        "0.0"
      ],
      [
        "Dec 17, 4:00 am",
        "32",
        "21",
        "S",
        "18G35",
        "13.9",
        "0.0",
        "0.0",
        "0.0"
      ],
      [
        "Dec 17, 3:00 am",
        "31",
        "20",
        "S",
        "15G35",
        "13.9",
        "0.0",
        "0.0",
        "0.0"
      ],
      [
        "Dec 17, 2:00 am",
        "30",
        "22",
        "S",
        "8G24",
        "14.0",
        "0.0",
        "0.0",
        "0.0"
      ],
      [
        "Dec 17, 1:00 am",
        "29",
        "22",
        "S",
        "7G16",
        "14.1",
        "0.1",
        "0.2",
        "0.0"
      ],
      [
        "Dec 17, 12:00 am",
        "29",
        "21",
        "SSW",
        "8G21",
        "14.1",
        "0.1",
        "0.2",
        "0.0"
      ],
      [
        "Dec 16, 11:00 pm",
        "30",
        "24",
        "S",
        "6G17",
        "14.0",
        "0.0",
        "0.0",
        "0.0"
      ],
      [
        "Dec 16, 10:00 pm",
        "30",
        "24",
        "SSW",
        "6G15",
        "14.0",
        "0.1",
        "0.0",
        "0.0"
      ],
      [
        "Dec 16, 9:00 pm",
        "30",
        "25",
        "SSW",
        "5G14",
        "14.0",
        "0.1",
        "0.0",
        "0.0"
      ],
      [
        "Dec 16, 8:00 pm",
        "31",
        "26",
        "SW",
        "5G18",
        "14.0",
        "0.0",
        "0.0",
        ""
      ],
      [
        "Dec 16, 7:00 pm",
        "32",
        "26",
        "SSW",
        "7G18",
        "13.9",
        "0.0",
        "0.0",
        ""
      ],
      [
        "Dec 16, 6:00 pm",
        "33",
        "27",
        "S",
        "7G31",
        "13.9",
        "0.0",
        "0.0",
        ""
      ],
      [
        "Dec 16, 5:00 pm",
        "33",
        "27",
        "SSW",
        "7G19",
        "76.5",
        "61.7",
        "0.0",
        ""
      ],
      [
        "Dec 16, 4:00 pm",
        "34",
        "27",
        "S",
        "8G25",
        "76.9",
        "0.4",
        "0.0",
        ""
      ],
      [
        "Dec 16, 3:00 pm",
        "33",
        "27",
        "SSW",
        "6G19",
        "76.7",
        "0.0",
        "0.8",
        ""
      ],
      [
        "Dec 16, 2:00 pm",
        "32",
        "27",
        "SW",
        "5G18",
        "14.8",
        "0.0",
        "0.8",
        ""
      ],
      [
        "Dec 16, 1:00 pm",
        "31",
        "26",
        "SW",
        "5G14",
        "76.5",
        "0.0",
        "62.4",
        ""
      ],
      [
        "Dec 16, 12:00 pm",
        "31",
        "25",
        "WSW",
        "6G21",
        "76.8",
        "0.9",
        "62.7",
        ""
      ],
      [
        "Dec 16, 11:00 am",
        "30",
        "25",
        "WSW",
        "5G16",
        "76.9",
        "62.9",
        "62.7",
        ""
      ],
      [
        "Dec 16, 10:00 am",
        "31",
        "26",
        "WSW",
        "5G19",
        "77.0",
        "62.9",
        "62.9",
        ""
      ],
      [
        "Dec 16, 9:00 am",
        "32",
        "26",
        "SW",
        "6G27",
        "75.9",
        "61.8",
        "61.7",
        ""
      ],
      [
        "Dec 16, 8:00 am",
        "32",
        "27",
        "SW",
        "5G19",
        "14.0",
        "0.0",
        "0.0",
        ""
      ],
      [
        "Dec 16, 7:00 am",
        "33",
        "27",
        "SW",
        "7G19",
        "14.1",
        "0.0",
        "0.0",
        ""
      ],
      [
        "Dec 16, 6:00 am",
        "33",
        "27",
        "WSW",
        "7G27",
        "14.1",
        "0.0",
        "0.0",
        ""
      ],
      [
        "Dec 16, 5:00 am",
        "33",
        "27",
        "SW",
        "7G21",
        "14.2",
        "0.0",
        "0.0",
        ""
      ],
      [
        "Dec 16, 4:00 am",
        "34",
        "26",
        "SSW",
        "10G37",
        "14.1",
        "0.0",
        "0.0",
        ""
      ],
      [
        "Dec 16, 3:00 am",
        "35",
        "27",
        "SSW",
        "10G35",
        "14.2",
        "0.0",
        "0.0",
        ""
      ],
      [
        "Dec 16, 2:00 am",
        "35",
        "27",
        "S",
        "10G26",
        "14.2",
        "0.0",
        "",
        ""
      ],
      [
        "Dec 16, 1:00 am",
        "35",
        "26",
        "S",
        "13G25",
        "14.2",
        "0.1",
        "",
        ""
      ],
      [
        "Dec 16, 12:00 am",
        "36",
        "27",
        "S",
        "13G30",
        "14.2",
        "0.0",
        "",
        ""
      ],
      [
        "Dec 15, 11:00 pm",
        "36",
        "29",
        "S",
        "10G26",
        "14.2",
        "",
        "",
        ""
      ],
      [
        "Dec 15, 10:00 pm",
        "36",
        "30",
        "SSW",
        "8G26",
        "14.1",
        "",
        "",
        ""
      ],
      [
        "Dec 15, 9:00 pm",
        "35",
        "29",
        "SSW",
        "7G20",
        "14.3",
        "",
        "",
        ""
      ]
    ]
  },
  "url": "https://www.weather.gov/wrh/timeseries?site=YCAND&hours=168&units=english&chart=on&headers=on&obs=tabular&hourly=false&pview=full&font=12&plot=",
  "sources": [
    "mtavalanche",
    "weather.gov"
  ],
  "mtavalanche_url": "https://www.mtavalanche.com/weather/yellowstoneclub/andesite"
}